pyTMGM.py
pytmgmOps.py
pytmgmOps-0.0.2.dist-info/LICENSE
pytmgmOps-0.0.2.dist-info/METADATA
pytmgmOps-0.0.2.dist-info/WHEEL
pytmgmOps-0.0.2.dist-info/top_level.txt
pytmgmOps-0.0.2.dist-info/RECORD
