Metadata-Version: 2.1
Name: pytmgmOps
Version: 0.0.2
Summary: TMGM Risk Used -- Bowen Yan
Home-page: UNKNOWN
Author: Bowen Yan (TMGM Risk)
Author-email: UNKNOWN
License: UNKNOWN
Platform: UNKNOWN
Requires-Dist: sqlalchemy
Requires-Dist: snowflake-connector-python
Requires-Dist: snowflake-sqlalchemy
Requires-Dist: pandas
Requires-Dist: pyathena
Requires-Dist: mysql-connector-python (==8.0.28)
